{"reviewSummary":{"completed":false},"mastheadScreenshot":{"fullRes":"//c.opencritic.com/images/games/1520/ITQu5qHcqvwH4tlLfc.jpg","thumbnail":"//c.opencritic.com/images/games/1520/ITQu5qHcqvwH4tlLfc_th.jpg"},"bannerScreenshot":{"fullRes":"//c.opencritic.com/images/games/1520/banner.jpg"},"newsSearchEnabled":true,"type":"BASE","Skus":["HB_dark-souls-iii-deluxe-edition","HB_dark-souls-iii","GMG_dark-souls-iii","GMG_dark-souls-iii-deluxe-edition","GP_2978-1","GP_2978-2","FN_dark-souls-iii-deluxe-edition","FN_dark-souls-iii","V_dark-souls-iii-deluxe-edition","V_dark-souls-iii","NZ_8a402903-37e3-4fe7-ae0c-b29cf256484e"],"percentRecommended":93.24324324324324,"numReviews":155,"numTopCriticReviews":128,"numUserReviews":1,"medianScore":90,"averageScore":89.73793103448276,"topCriticScore":89.703125,"percentile":98,"tier":"Mighty","hasLootBoxes":false,"isMajorTitle":true,"name":"Dark Souls III","description":"Dark Souls III continues to push the boundaries with the latest, ambitious chapter in critically-acclaimed and genre-defining series. As fires fade and only embers remain, journey once more into a world filled with more daunting and colossal enemies and environments. Players will be immersed into a world of epic atmosphere and darkness through faster gameplay and amplified combat intensity. New to the series are the Battle Arts attacks. You'll be able to deliver powerful attacks that will break through enemy defenses. Each weapon will have its own unique Battle Arts.","screenshots":[{"fullRes":"//c.opencritic.com/images/games/1520/8XPWCd5TqxguuF3v10CNlAxfBpU2XAMH.jpg","thumbnail":"//c.opencritic.com/images/games/1520/8XPWCd5TqxguuF3v10CNlAxfBpU2XAMH_th.jpg"},{"fullRes":"//c.opencritic.com/images/games/1520/8uFkHPLvtjZQ6Z8iuwU7KsISDOaJ0avA.jpg","thumbnail":"//c.opencritic.com/images/games/1520/8uFkHPLvtjZQ6Z8iuwU7KsISDOaJ0avA_th.jpg"},{"fullRes":"//c.opencritic.com/images/games/1520/N8XAz6mahUg3QIbMCYzXo9GQDE8jDmnm.jpg","thumbnail":"//c.opencritic.com/images/games/1520/N8XAz6mahUg3QIbMCYzXo9GQDE8jDmnm_th.jpg"}],"trailers":[{"publishedDate":"2015-08-04T00:00:00.000Z","title":"Dark Souls™ III – Gameplay Reveal Trailer","videoId":"2HIxuGi_2TQ","externalUrl":"https://www.youtube.com/watch?v=2HIxuGi_2TQ","channelTitle":"Bandai Namco Entertainment America","channelId":"UC_ntXHv-XdKCD7CPynVvnQw","description":"Dark Souls III continues to push the boundaries with the latest, ambitious chapter in critically-acclaimed and genre-defining series.  As fires fade and only embers remain, journey once more into a world filled with more daunting and colossal enemies and environments.   Players will be immersed into a world of epic atmosphere and darkness through faster gameplay and amplified combat intensity.  New to the series are the Battle Arts attacks.   You'll be able to deliver powerful attacks that will break through enemy defenses.  Each weapon will have its own unique Battle Arts.   \n\nEmbrace The Darkness!\nEarly 2016\n\nLearn More: http://www.darksouls3.com/us/\n\nJoin the Dark Souls Community: \nTwitter: http://www.twitter.com/darksoulsgame\nFacebook: http://www.facebook.com/darksouls\nInstagram: http://instagram.com/darksoulsgame\nTumblr: http://darksoulsgame.tumblr.com/\n\nFollow Bandai Namco Games:\nFacebook: https://www.facebook.com/BandaiNamcoUS\nTwitter: https://twitter.com/BandaiNamcoUS/\nTumblr: http://bandainamcous.tumblr.com/\nTwitch: http://www.twitch.tv/bandainamcous","lastRefreshDate":"2021-06-02T15:48:35.741Z"}],"twitchName":"Dark Souls III","embargoDate":"2016-04-04T07:03:00.000Z","steamId":"374320","Companies":[{"name":"Bandai Namco Games","type":"PUBLISHER"},{"name":"FromSoftware","type":"DEVELOPER"}],"Platforms":[{"id":6,"name":"PlayStation 4","shortName":"PS4","imageSrc":"https://c.opencritic.com/images/platforms/ps4.png","releaseDate":"2016-04-12T00:00:00.000Z","displayRelease":null},{"id":7,"name":"Xbox One","shortName":"XB1","imageSrc":"https://c.opencritic.com/images/platforms/xb1.png","releaseDate":"2016-04-12T00:00:00.000Z","displayRelease":null},{"id":27,"name":"PC","shortName":"PC","imageSrc":"https://c.opencritic.com/images/platforms/pc.png","releaseDate":"2016-04-12T00:00:00.000Z","displayRelease":null},{"id":2,"name":"Xbox Series X/S","shortName":"XBXS","imageSrc":"https://c.opencritic.com/images/platforms/xbxs.png","releaseDate":"2020-11-10T00:00:00.000Z"},{"id":3,"name":"PlayStation 5","shortName":"PS5","imageSrc":"https://c.opencritic.com/images/platforms/ps5.png","releaseDate":"2020-11-12T00:00:00.000Z"}],"Genres":[{"id":27,"name":"Action"}],"Affiliates":[{"externalUrl":"https://us.gamesplanet.com/game/stuff--2978-1?ref=opencritic","name":"GamesPlanet"},{"externalUrl":"http://www.anrdoezrs.net/links/8050398/type/dlg/https://www.greenmangaming.com/games/dark-souls-iii-deluxe-edition","name":"Green Man Gaming"},{"externalUrl":"http://www.anrdoezrs.net/links/8050398/type/dlg/https://www.fanatical.com/en/game/dark-souls-iii-deluxe-edition","name":"Fanatical"},{"externalUrl":"https://lt45.net/c/?si=12328&li=1541858&wi=343735&ws=&dl=en%2Fdark-souls-iii-deluxe-edition","name":"Voidu"}],"id":1520,"firstReleaseDate":"2016-04-12T00:00:00.000Z","createdAt":"2019-09-21T18:53:48.164Z","updatedAt":"2021-06-02T15:48:35.746Z","firstReviewDate":"2016-03-27T04:00:00.000Z","latestReviewDate":"2017-10-22T04:00:00.000Z"}